pl_extension/__init__.py
pl_extension/trainer_io.py
pl_extension/callbacks/__init__.py
pl_extension/callbacks/evaluation.py
pl_extension/callbacks/linear_scaling_rule.py
pl_extension/callbacks/lr_scheduler.py
pl_extension/callbacks/speed.py
pl_extension/loggers/__init__.py
pl_extension/loggers/logging_logger.py
pl_extension/loggers/mlflow_logger.py
pl_extension/utilities/__init__.py
pl_extension/utilities/config.py
pl_extension/utilities/env.py
pl_extension/utilities/file_io.py
pl_extension/utilities/logger.py
pl_extension/utilities/rand.py
pl_extension-0.0.7.dist-info/LICENSE
pl_extension-0.0.7.dist-info/METADATA
pl_extension-0.0.7.dist-info/WHEEL
pl_extension-0.0.7.dist-info/top_level.txt
pl_extension-0.0.7.dist-info/RECORD
