Metadata-Version: 2.2
Name: pl-extension
Version: 0.0.7
Summary: extension for pytorch-lightning
Home-page: https://github.com/duinodu/pl-extension
Author: duinodu
Author-email: 472365351duino@gmail.com
License: Apache License
Project-URL: Bug Tracker, https://github.com/duinodu/pl-extension/issues
Requires-Python: >=3.6
License-File: LICENSE
Requires-Dist: iopath
Requires-Dist: termcolor
Requires-Dist: lightning
Dynamic: author
Dynamic: author-email
Dynamic: description
Dynamic: home-page
Dynamic: license
Dynamic: project-url
Dynamic: requires-dist
Dynamic: requires-python
Dynamic: summary
